README.md
setup.py
Sookie_Django_Query.egg-info/PKG-INFO
Sookie_Django_Query.egg-info/SOURCES.txt
Sookie_Django_Query.egg-info/dependency_links.txt
Sookie_Django_Query.egg-info/not-zip-safe
Sookie_Django_Query.egg-info/requires.txt
Sookie_Django_Query.egg-info/top_level.txt
sookie_django_query/AndCondition.py
sookie_django_query/BaseQuery.py
sookie_django_query/BetweenCondition.py
sookie_django_query/BetweenConditionBuilder.py
sookie_django_query/CommonExpressBuilder.py
sookie_django_query/ConditionInterface.py
sookie_django_query/ConjunctionCondition.py
sookie_django_query/ConjunctionConditionBuilder.py
sookie_django_query/DB.py
sookie_django_query/ExpressionInterface.py
sookie_django_query/Handler.py
sookie_django_query/HashCondition.py
sookie_django_query/HashConditionBuilder.py
sookie_django_query/InCondition.py
sookie_django_query/InConditionBuilder.py
sookie_django_query/LikeCondition.py
sookie_django_query/LikeConditionBuilder.py
sookie_django_query/MysqlDB.py
sookie_django_query/NotCondition.py
sookie_django_query/NotConditionBuilder.py
sookie_django_query/OrCondition.py
sookie_django_query/PoolDB.py
sookie_django_query/Query.py
sookie_django_query/QueryBuilder.py
sookie_django_query/SimpleCondition.py
sookie_django_query/SimpleConditionBuilder.py
sookie_django_query/__init__.py