Metadata-Version: 1.1
Name: Sookie-Django-Query
Version: 0.0.1
Summary: 通过对象创建sql语句
Home-page: https://github.com/huangdingbo/django-query
Author: Billy J. Hee
Author-email: 378969398@qq.com
License: BSD
Platform: any
Classifier: Environment :: Web Environment
Classifier: Intended Audience :: Developers
Classifier: License :: OSI Approved :: BSD License
Classifier: Operating System :: OS Independent
Classifier: Programming Language :: Python
Classifier: Topic :: Internet :: WWW/HTTP :: Dynamic Content
Classifier: Topic :: Software Development :: Libraries :: Python Modules
